{
  "title": "best ai ai tool for photo to cartoon",
  "description": "Transform Your Stories & Photos into Cartoon Books Transform Your Stories & Photos into Cartoon Books. DreamCanvas is an AI-powered tool that transforms photos into cartoon books and animated stories, creating a unique storytelling experience. Users can upload photos to the platform, which are then converted into characters for personalized stories. Additionally, the tool provides a feature to. Key strengths include transforms photos into cartoons, creates animated stories, generates personalized story characters. If you need a AI solution with clear outcomes, DreamCanvas is worth evaluating in your shortlist. This listing is relevant for searches like \"best ai ai tool for photo to cartoon\" and \"dreamcanvas alternative for storytelling\". Best suited for: Best for teams looking for ai workflows with practical outcomes and measurable productivity gains. Key capabilities include Transforms photos into cartoons, Creates animated stories, Generates personalized story characters, Generates dialogues and emotions, Creates evolving story narratives. Validate output quality using your own real dataset before team-wide rollout. Check pricing and plan limits against expected monthly usage. Confirm privacy, security, and compliance requirements for your use case.",
  "tags": [
    "photo to cartoon",
    "storytelling",
    "story automation",
    "cartoon book creation",
    "personalized content",
    "animation",
    "AI tools",
    "artificial intelligence",
    "photo",
    "cartoon"
  ],
  "category": "Technology / AI",
  "toolTitle": "DreamCanvas",
  "toolSlug": "dreamcanvas",
  "permalink": "https://aitoolslist.xyz/dreamcanvas/"
}