{
  "title": "best ai ai tool for file interaction",
  "description": "Revolutionizing team knowledge with AI-driven file and folder interaction. Revolutionizing team knowledge with AI-driven file and folder interaction. Amigotor is an artificial intelligence tool that is designed to animate your files, folders, and team knowledge base. This AI tool serves as a personalized chat bot, encouraging interactions with your documents as though you are talking to a real person. It is capable of converting various file. Key strengths include personalized chat bot, supports various file types, enables conversations with files. If you need a AI solution with clear outcomes, Amigotor is worth evaluating in your shortlist. This listing is relevant for searches like \"best ai ai tool for file interaction\" and \"amigotor alternative for knowledge management\". Best suited for: Best for teams looking for ai workflows with practical outcomes and measurable productivity gains. Key capabilities include Personalized chat bot, Supports various file types, Enables conversations with files, Can ask questions, write summaries. Validate output quality using your own real dataset before team-wide rollout. Check pricing and plan limits against expected monthly usage. Confirm privacy, security, and compliance requirements for your use case.",
  "tags": [
    "File Interaction",
    "Knowledge Management",
    "Conversational AI",
    "Chatbot",
    "File Conversion",
    "Document Analysis",
    "AI tools",
    "artificial intelligence",
    "interaction"
  ],
  "category": "Technology / AI",
  "toolTitle": "Amigotor",
  "toolSlug": "amigotor",
  "permalink": "https://aitoolslist.xyz/amigotor/"
}