{
  "title": "best ai ai tool for businessplangenerator",
  "description": "From a blank page to a professional business plan in a few clicks From a blank page to a professional business plan in a few clicks. BizPlanner AI is an AI-driven platform designed to facilitate the creation of professional business plans with efficiency and ease. It guides users through a streamlined process, starting from a blank page and culminating in a comprehensive business plan tailored to their specific needs. With its. Key strengths include automated business plan drafting, intuitive user platform, customization based on questionnaire. If you need a AI solution with clear outcomes, BizPlanner AI is worth evaluating in your shortlist. This listing is relevant for searches like \"best ai ai tool for businessplangenerator\" and \"bizplanner ai alternative for professionalplanning\". Best suited for: Best for teams looking for ai workflows with practical outcomes and measurable productivity gains. Key capabilities include Automated business plan drafting, Intuitive user platform, Customization based on questionnaire, Comprehensive business plan structure, Includes market research section. Validate output quality using your own real dataset before team-wide rollout. Check pricing and plan limits against expected monthly usage. Confirm privacy, security, and compliance requirements for your use case.",
  "tags": [
    "BusinessPlanGenerator",
    "ProfessionalPlanning",
    "EfficientSolutions",
    "CustomizedPlans",
    "BusinessStrategy",
    "BusinessSuccess",
    "AI tools",
    "artificial intelligence",
    "businessplangenerator"
  ],
  "category": "Technology / AI",
  "toolTitle": "BizPlanner AI",
  "toolSlug": "bizplanner-ai",
  "permalink": "https://aitoolslist.xyz/bizplanner-ai/"
}